Wii/NUStool.py
Wii/Struct.py
Wii/__init__.py
Wii/archive.py
Wii/bns.py
Wii/common.py
Wii/compression.py
Wii/disc.py
Wii/export.py
Wii/formats.py
Wii/headers.py
Wii/image.py
Wii/mymenu.py
Wii/nand.py
Wii/nus_downloader.py
Wii/title.py
Wii/wiimposter.py
Wii.py-0.2.dist-info/LICENSE
Wii.py-0.2.dist-info/METADATA
Wii.py-0.2.dist-info/WHEEL
Wii.py-0.2.dist-info/top_level.txt
Wii.py-0.2.dist-info/RECORD
