Metadata-Version: 2.1
Name: Wii.py
Version: 0.2
Summary: Wii library written in and for Python
Home-page: https://github.com/DorkmasterFlek/Wii.py
Author: Xuzz, SquidMan, megazig, Matt_P, Omega, The Lemon Man, marcan, Daeken
Author-email: 
Maintainer: Dorkmaster Flek
Maintainer-email: dorkmasterflek@gmail.com
License: GNU GPL v3
Platform: UNKNOWN
Requires-Python: >=2.7, >=3.3
Requires-Dist: cryptography
Requires-Dist: Pillow
Provides-Extra: gui
Requires-Dist: wxPython ; extra == 'gui'
